{"commands": {
	"l": "look",

	"i": "inventory",
	"inv": "inventory",

	"commands": "help",
	"?": "help",
	"cmds": "help",

	"travel": "go",
	"climb": "go",

	"n": "north",
	"s": "south",
	"e": "east",
	"w": "west",
	"nw": "northwest",
	"ne": "northeast",
	"se": "southeast",
	"sw": "southwest",

	"u": "up",
	"d": "down",

	"inspect": "examine",
	"check": "examine",

	"grab": "get",
	"take": "get",
	"pick": "get",
	"pickup": "get",

	"leave": "drop",
	"throw": "drop",

	"shut": "close",

	"press": "push",

	"punch": "hit",
	"kick": "hit",
	"attack": "hit",
	"headbutt": "hit"
}}
